tree_sitter_odin-1.3.0.dist-info/top_level.txt
tree_sitter_odin-1.3.0.dist-info/RECORD
tree_sitter_odin-1.3.0.dist-info/LICENSE
tree_sitter_odin-1.3.0.dist-info/METADATA
tree_sitter_odin-1.3.0.dist-info/WHEEL
tree_sitter_odin/__init__.py
tree_sitter_odin/_binding.abi3.so
tree_sitter_odin/binding.c
tree_sitter_odin/__init__.pyi
tree_sitter_odin/py.typed
tree_sitter_odin/queries/folds.scm
tree_sitter_odin/queries/highlights.scm
tree_sitter_odin/queries/indents.scm
tree_sitter_odin/queries/injections.scm
tree_sitter_odin/queries/locals.scm
